{
  "gitSyncId": "675405067f806e6071e752a7_1983612a-d846-4ec2-a5ea-c48ec08c0e05",
  "id": "User_getYourTask",
  "pluginId": "postgres-plugin",
  "pluginType": "DB",
  "unpublishedAction": {
    "actionConfiguration": {
      "body": "SELECT * \nFROM public.assignment\nINNER JOIN public.task\nON public.task.id= public.assignment.task_id\nINNER JOIN public.volunteerprofiles\nON public.volunteerprofiles.id = public.assignment.volunteer_profile_id\nINNER JOIN public.address\nON public.address.address_id= public.task.address_id\nWHERE public.volunteerprofiles.user_id = {{appsmith.store.user_profile.id}}\n",
      "encodeParamsToggle": true,
      "paginationType": "NONE",
      "pluginSpecifiedTemplates": [
        {
          "value": true
        }
      ],
      "timeoutInMillisecond": 10000
    },
    "confirmBeforeExecute": false,
    "datasource": {
      "id": "SafeU_DB",
      "isAutoGenerated": false,
      "name": "SafeU_DB",
      "pluginId": "postgres-plugin"
    },
    "dynamicBindingPathList": [
      {
        "key": "body"
      }
    ],
    "executeOnLoad": true,
    "name": "getYourTask",
    "pageId": "User",
    "userSetOnLoad": false
  }
}